{
    "url": "https://www.ukpol.co.uk/john-hayes-2011-speech-to-the-association-for-careers-education-and-guidance-annual-conference/",
    "title": "John Hayes \u2013 2011 Speech to the Association for Careers Education and Guidance Annual Conference",
    "post_date": "September 15, 2022",
    "author": "admin",
    "tags": [
        {
            "text": "2011",
            "url": "/tag/2011/"
        },
        {
            "text": "John Hayes",
            "url": "/tag/john-hayes/"
        },
        {
            "text": "Speeches",
            "url": "/tag/speeches/"
        }
    ],
    "categories": [
        {
            "text": "Education",
            "url": "/category/education/"
        },
        {
            "text": "Speeches",
            "url": "/category/speeches/"
        }
    ],
    "summary": "The speech made by John Hayes, the then Education Minister, in Thame, Oxfordshire on 7 July 2011.",
    "content": []
}