{
    "url": "https://www.ukpol.co.uk/penny-mordaunt-2022-statement-on-the-replacement-of-the-chancellor-of-the-exchequer/",
    "title": "Penny Mordaunt \u2013 2022 Statement on the Replacement of the Chancellor of the Exchequer",
    "post_date": "October 17, 2022",
    "author": "admin",
    "tags": [
        {
            "text": "2022",
            "url": "/tag/2022/"
        },
        {
            "text": "Penny Mordaunt",
            "url": "/tag/penny-mordaunt/"
        },
        {
            "text": "Speeches",
            "url": "/tag/speeches/"
        }
    ],
    "categories": [
        {
            "text": "Parliament",
            "url": "/category/parliament/"
        },
        {
            "text": "Speeches",
            "url": "/category/speeches/"
        }
    ],
    "summary": "The statement made by Penny Mordaunt, the Leader of the House of Commons, in the House on 17 October 2022 following a urgent Parliamentary question from Keir Starmer, the Leader of the Opposition.",
    "content": [
        "**Keir Starmer (Holborn and St Pancras) (Lab)**\n  *[ISIL]: Islamic State of Iraq and the Levant\n  *[SDGs]: Sustainable Development Goals\n  *[IMF]: International Monetary Fund\n  *[UN]: United Nations\n  *[GDP]: Gross Domestic Product\n  *[UCL]: University College London\n  *[HIV]: human immunodeficiency virus\n  *[AI]: artificial intelligence\n  *[ABI]: Association of British Insurers\n  *[CMU]: Capital Markets Union\n  *[IMO]: International Maritime Organization\n  *[MARPOL]: International Convention for the Prevention of Pollution from Ships.\n  *[UK]: United Kingdom\n  *[IGF]: International Code of Safety for Ships using Gases or other Low-flashpoint Fuels\n  *[COP]: United Nations Climate Change Conference (Conference of Parties)\n  *[AOA]: The Airport Operators Association\n  *[BATA]: British Air Transport Association\n  *[OECD]: The Organisation for Economic Co-operation and Development\n  *[PISA]: Programme for International Student Assessment\n  *[PIRLS]: Progress in International Reading Literacy Study\n  *[TIMSS]: Trends in International Mathematics and Science Study\n  *[DCMS]: Department for Digital Culture Media & Sport\n  *[CEOs]: chief executive officers\n  *[HR]: human resources\n  *[NASBM]: National Association of School Business Management\n  *[CAMHS]: Child and Adolescent Mental Health Services\n  *[EPPSE]: Effective pre-school, primary and secondary education\n  *[LAs]: local authorities\n  *[PVIs]: private, voluntary and independents\n  *[UNDP]: United Nations Development Programme\n  *[BIT]: Behavioural Insights Team\n  *[QOF]: Quality Outcomes Framework\n  *[\n  NICs\n ]: National Insurance Contributions\n  *[UKTI]: UK Trade and Investment\n  *[IPOs]: initial public offerings\n  *[DfE]: Department for Education\n  *[FSM]: free school meals\n  *[RAISEonline]: Reporting and Analysis for Improvement through School Self Evaluation Online\n  *[GSHA]: Grammar School Heads Association\n  *[OSA]: Office of the Schools Adjudicator\n  *[LACA]: Leading Association for Catering in Education\n  *[ODA]: Official Development Assistance\n  *[NGOs]: non-governmental organisations\n  *[NGO]: non-governmental organisation\n  *[BII]: British Investment International\n  *[DFID]: Department for International Development\n  *[UKEF]: UK Export Finance\n  *[COPs]: *[COP]: United Nations Climate Change Conferences\n  *[UNGA]: United Nations General Assembly\n  *[IDA]: International Development Association\n  *[IBRD]: International Bank for Reconstruction and Development\n  *[IFC]: International Finance Corporation\n  *[IDA20]: World Bank launched an early twentieth replenishment process of the International Development Association\n  *[SDG]: Sustainable Development Goal\n  *[GRF]: Global Refugee Forum\n  *[SAF]: Sudanese Armed Forces\n  *[RSF]: Rapid Support Forces",
        "(Urgent Question): To ask the Prime Minister to make a statement on the replacement of the Chancellor of the Exchequer during the current economic situation.\n  *[ISIL]: Islamic State of Iraq and the Levant\n  *[SDGs]: Sustainable Development Goals\n  *[IMF]: International Monetary Fund\n  *[UN]: United Nations\n  *[GDP]: Gross Domestic Product\n  *[UCL]: University College London\n  *[HIV]: human immunodeficiency virus\n  *[AI]: artificial intelligence\n  *[ABI]: Association of British Insurers\n  *[CMU]: Capital Markets Union\n  *[IMO]: International Maritime Organization\n  *[MARPOL]: International Convention for the Prevention of Pollution from Ships.\n  *[UK]: United Kingdom\n  *[IGF]: International Code of Safety for Ships using Gases or other Low-flashpoint Fuels\n  *[COP]: United Nations Climate Change Conference (Conference of Parties)\n  *[AOA]: The Airport Operators Association\n  *[BATA]: British Air Transport Association\n  *[OECD]: The Organisation for Economic Co-operation and Development\n  *[PISA]: Programme for International Student Assessment\n  *[PIRLS]: Progress in International Reading Literacy Study\n  *[TIMSS]: Trends in International Mathematics and Science Study\n  *[DCMS]: Department for Digital Culture Media & Sport\n  *[CEOs]: chief executive officers\n  *[HR]: human resources\n  *[NASBM]: National Association of School Business Management\n  *[CAMHS]: Child and Adolescent Mental Health Services\n  *[EPPSE]: Effective pre-school, primary and secondary education\n  *[LAs]: local authorities\n  *[PVIs]: private, voluntary and independents\n  *[UNDP]: United Nations Development Programme\n  *[BIT]: Behavioural Insights Team\n  *[QOF]: Quality Outcomes Framework\n  *[\n  NICs\n ]: National Insurance Contributions\n  *[UKTI]: UK Trade and Investment\n  *[IPOs]: initial public offerings\n  *[DfE]: Department for Education\n  *[FSM]: free school meals\n  *[RAISEonline]: Reporting and Analysis for Improvement through School Self Evaluation Online\n  *[GSHA]: Grammar School Heads Association\n  *[OSA]: Office of the Schools Adjudicator\n  *[LACA]: Leading Association for Catering in Education\n  *[ODA]: Official Development Assistance\n  *[NGOs]: non-governmental organisations\n  *[NGO]: non-governmental organisation\n  *[BII]: British Investment International\n  *[DFID]: Department for International Development\n  *[UKEF]: UK Export Finance\n  *[COPs]: *[COP]: United Nations Climate Change Conferences\n  *[UNGA]: United Nations General Assembly\n  *[IDA]: International Development Association\n  *[IBRD]: International Bank for Reconstruction and Development\n  *[IFC]: International Finance Corporation\n  *[IDA20]: World Bank launched an early twentieth replenishment process of the International Development Association\n  *[SDG]: Sustainable Development Goal\n  *[GRF]: Global Refugee Forum\n  *[SAF]: Sudanese Armed Forces\n  *[RSF]: Rapid Support Forces",
        "**The Leader of the House of Commons (Penny Mordaunt)**\n  *[ISIL]: Islamic State of Iraq and the Levant\n  *[SDGs]: Sustainable Development Goals\n  *[IMF]: International Monetary Fund\n  *[UN]: United Nations\n  *[GDP]: Gross Domestic Product\n  *[UCL]: University College London\n  *[HIV]: human immunodeficiency virus\n  *[AI]: artificial intelligence\n  *[ABI]: Association of British Insurers\n  *[CMU]: Capital Markets Union\n  *[IMO]: International Maritime Organization\n  *[MARPOL]: International Convention for the Prevention of Pollution from Ships.\n  *[UK]: United Kingdom\n  *[IGF]: International Code of Safety for Ships using Gases or other Low-flashpoint Fuels\n  *[COP]: United Nations Climate Change Conference (Conference of Parties)\n  *[AOA]: The Airport Operators Association\n  *[BATA]: British Air Transport Association\n  *[OECD]: The Organisation for Economic Co-operation and Development\n  *[PISA]: Programme for International Student Assessment\n  *[PIRLS]: Progress in International Reading Literacy Study\n  *[TIMSS]: Trends in International Mathematics and Science Study\n  *[DCMS]: Department for Digital Culture Media & Sport\n  *[CEOs]: chief executive officers\n  *[HR]: human resources\n  *[NASBM]: National Association of School Business Management\n  *[CAMHS]: Child and Adolescent Mental Health Services\n  *[EPPSE]: Effective pre-school, primary and secondary education\n  *[LAs]: local authorities\n  *[PVIs]: private, voluntary and independents\n  *[UNDP]: United Nations Development Programme\n  *[BIT]: Behavioural Insights Team\n  *[QOF]: Quality Outcomes Framework\n  *[\n  NICs\n ]: National Insurance Contributions\n  *[UKTI]: UK Trade and Investment\n  *[IPOs]: initial public offerings\n  *[DfE]: Department for Education\n  *[FSM]: free school meals\n  *[RAISEonline]: Reporting and Analysis for Improvement through School Self Evaluation Online\n  *[GSHA]: Grammar School Heads Association\n  *[OSA]: Office of the Schools Adjudicator\n  *[LACA]: Leading Association for Catering in Education\n  *[ODA]: Official Development Assistance\n  *[NGOs]: non-governmental organisations\n  *[NGO]: non-governmental organisation\n  *[BII]: British Investment International\n  *[DFID]: Department for International Development\n  *[UKEF]: UK Export Finance\n  *[COPs]: *[COP]: United Nations Climate Change Conferences\n  *[UNGA]: United Nations General Assembly\n  *[IDA]: International Development Association\n  *[IBRD]: International Bank for Reconstruction and Development\n  *[IFC]: International Finance Corporation\n  *[IDA20]: World Bank launched an early twentieth replenishment process of the International Development Association\n  *[SDG]: Sustainable Development Goal\n  *[GRF]: Global Refugee Forum\n  *[SAF]: Sudanese Armed Forces\n  *[RSF]: Rapid Support Forces",
        "With apologies to the Leader of the Opposition and the House, the Prime Minister is detained on urgent business\u2014[Interruption.]\u2014and they will have to make do\u2014[Interruption.]\n  *[ISIL]: Islamic State of Iraq and the Levant\n  *[SDGs]: Sustainable Development Goals\n  *[IMF]: International Monetary Fund\n  *[UN]: United Nations\n  *[GDP]: Gross Domestic Product\n  *[UCL]: University College London\n  *[HIV]: human immunodeficiency virus\n  *[AI]: artificial intelligence\n  *[ABI]: Association of British Insurers\n  *[CMU]: Capital Markets Union\n  *[IMO]: International Maritime Organization\n  *[MARPOL]: International Convention for the Prevention of Pollution from Ships.\n  *[UK]: United Kingdom\n  *[IGF]: International Code of Safety for Ships using Gases or other Low-flashpoint Fuels\n  *[COP]: United Nations Climate Change Conference (Conference of Parties)\n  *[AOA]: The Airport Operators Association\n  *[BATA]: British Air Transport Association\n  *[OECD]: The Organisation for Economic Co-operation and Development\n  *[PISA]: Programme for International Student Assessment\n  *[PIRLS]: Progress in International Reading Literacy Study\n  *[TIMSS]: Trends in International Mathematics and Science Study\n  *[DCMS]: Department for Digital Culture Media & Sport\n  *[CEOs]: chief executive officers\n  *[HR]: human resources\n  *[NASBM]: National Association of School Business Management\n  *[CAMHS]: Child and Adolescent Mental Health Services\n  *[EPPSE]: Effective pre-school, primary and secondary education\n  *[LAs]: local authorities\n  *[PVIs]: private, voluntary and independents\n  *[UNDP]: United Nations Development Programme\n  *[BIT]: Behavioural Insights Team\n  *[QOF]: Quality Outcomes Framework\n  *[\n  NICs\n ]: National Insurance Contributions\n  *[UKTI]: UK Trade and Investment\n  *[IPOs]: initial public offerings\n  *[DfE]: Department for Education\n  *[FSM]: free school meals\n  *[RAISEonline]: Reporting and Analysis for Improvement through School Self Evaluation Online\n  *[GSHA]: Grammar School Heads Association\n  *[OSA]: Office of the Schools Adjudicator\n  *[LACA]: Leading Association for Catering in Education\n  *[ODA]: Official Development Assistance\n  *[NGOs]: non-governmental organisations\n  *[NGO]: non-governmental organisation\n  *[BII]: British Investment International\n  *[DFID]: Department for International Development\n  *[UKEF]: UK Export Finance\n  *[COPs]: *[COP]: United Nations Climate Change Conferences\n  *[UNGA]: United Nations General Assembly\n  *[IDA]: International Development Association\n  *[IBRD]: International Bank for Reconstruction and Development\n  *[IFC]: International Finance Corporation\n  *[IDA20]: World Bank launched an early twentieth replenishment process of the International Development Association\n  *[SDG]: Sustainable Development Goal\n  *[GRF]: Global Refugee Forum\n  *[SAF]: Sudanese Armed Forces\n  *[RSF]: Rapid Support Forces",
        "**Mr Speaker**\n  *[ISIL]: Islamic State of Iraq and the Levant\n  *[SDGs]: Sustainable Development Goals\n  *[IMF]: International Monetary Fund\n  *[UN]: United Nations\n  *[GDP]: Gross Domestic Product\n  *[UCL]: University College London\n  *[HIV]: human immunodeficiency virus\n  *[AI]: artificial intelligence\n  *[ABI]: Association of British Insurers\n  *[CMU]: Capital Markets Union\n  *[IMO]: International Maritime Organization\n  *[MARPOL]: International Convention for the Prevention of Pollution from Ships.\n  *[UK]: United Kingdom\n  *[IGF]: International Code of Safety for Ships using Gases or other Low-flashpoint Fuels\n  *[COP]: United Nations Climate Change Conference (Conference of Parties)\n  *[AOA]: The Airport Operators Association\n  *[BATA]: British Air Transport Association\n  *[OECD]: The Organisation for Economic Co-operation and Development\n  *[PISA]: Programme for International Student Assessment\n  *[PIRLS]: Progress in International Reading Literacy Study\n  *[TIMSS]: Trends in International Mathematics and Science Study\n  *[DCMS]: Department for Digital Culture Media & Sport\n  *[CEOs]: chief executive officers\n  *[HR]: human resources\n  *[NASBM]: National Association of School Business Management\n  *[CAMHS]: Child and Adolescent Mental Health Services\n  *[EPPSE]: Effective pre-school, primary and secondary education\n  *[LAs]: local authorities\n  *[PVIs]: private, voluntary and independents\n  *[UNDP]: United Nations Development Programme\n  *[BIT]: Behavioural Insights Team\n  *[QOF]: Quality Outcomes Framework\n  *[\n  NICs\n ]: National Insurance Contributions\n  *[UKTI]: UK Trade and Investment\n  *[IPOs]: initial public offerings\n  *[DfE]: Department for Education\n  *[FSM]: free school meals\n  *[RAISEonline]: Reporting and Analysis for Improvement through School Self Evaluation Online\n  *[GSHA]: Grammar School Heads Association\n  *[OSA]: Office of the Schools Adjudicator\n  *[LACA]: Leading Association for Catering in Education\n  *[ODA]: Official Development Assistance\n  *[NGOs]: non-governmental organisations\n  *[NGO]: non-governmental organisation\n  *[BII]: British Investment International\n  *[DFID]: Department for International Development\n  *[UKEF]: UK Export Finance\n  *[COPs]: *[COP]: United Nations Climate Change Conferences\n  *[UNGA]: United Nations General Assembly\n  *[IDA]: International Development Association\n  *[IBRD]: International Bank for Reconstruction and Development\n  *[IFC]: International Finance Corporation\n  *[IDA20]: World Bank launched an early twentieth replenishment process of the International Development Association\n  *[SDG]: Sustainable Development Goal\n  *[GRF]: Global Refugee Forum\n  *[SAF]: Sudanese Armed Forces\n  *[RSF]: Rapid Support Forces",
        "Order. I must hear the answer to why the Prime Minister is not here.\n  *[ISIL]: Islamic State of Iraq and the Levant\n  *[SDGs]: Sustainable Development Goals\n  *[IMF]: International Monetary Fund\n  *[UN]: United Nations\n  *[GDP]: Gross Domestic Product\n  *[UCL]: University College London\n  *[HIV]: human immunodeficiency virus\n  *[AI]: artificial intelligence\n  *[ABI]: Association of British Insurers\n  *[CMU]: Capital Markets Union\n  *[IMO]: International Maritime Organization\n  *[MARPOL]: International Convention for the Prevention of Pollution from Ships.\n  *[UK]: United Kingdom\n  *[IGF]: International Code of Safety for Ships using Gases or other Low-flashpoint Fuels\n  *[COP]: United Nations Climate Change Conference (Conference of Parties)\n  *[AOA]: The Airport Operators Association\n  *[BATA]: British Air Transport Association\n  *[OECD]: The Organisation for Economic Co-operation and Development\n  *[PISA]: Programme for International Student Assessment\n  *[PIRLS]: Progress in International Reading Literacy Study\n  *[TIMSS]: Trends in International Mathematics and Science Study\n  *[DCMS]: Department for Digital Culture Media & Sport\n  *[CEOs]: chief executive officers\n  *[HR]: human resources\n  *[NASBM]: National Association of School Business Management\n  *[CAMHS]: Child and Adolescent Mental Health Services\n  *[EPPSE]: Effective pre-school, primary and secondary education\n  *[LAs]: local authorities\n  *[PVIs]: private, voluntary and independents\n  *[UNDP]: United Nations Development Programme\n  *[BIT]: Behavioural Insights Team\n  *[QOF]: Quality Outcomes Framework\n  *[\n  NICs\n ]: National Insurance Contributions\n  *[UKTI]: UK Trade and Investment\n  *[IPOs]: initial public offerings\n  *[DfE]: Department for Education\n  *[FSM]: free school meals\n  *[RAISEonline]: Reporting and Analysis for Improvement through School Self Evaluation Online\n  *[GSHA]: Grammar School Heads Association\n  *[OSA]: Office of the Schools Adjudicator\n  *[LACA]: Leading Association for Catering in Education\n  *[ODA]: Official Development Assistance\n  *[NGOs]: non-governmental organisations\n  *[NGO]: non-governmental organisation\n  *[BII]: British Investment International\n  *[DFID]: Department for International Development\n  *[UKEF]: UK Export Finance\n  *[COPs]: *[COP]: United Nations Climate Change Conferences\n  *[UNGA]: United Nations General Assembly\n  *[IDA]: International Development Association\n  *[IBRD]: International Bank for Reconstruction and Development\n  *[IFC]: International Finance Corporation\n  *[IDA20]: World Bank launched an early twentieth replenishment process of the International Development Association\n  *[SDG]: Sustainable Development Goal\n  *[GRF]: Global Refugee Forum\n  *[SAF]: Sudanese Armed Forces\n  *[RSF]: Rapid Support Forces",
        "**Penny Mordaunt**\n  *[ISIL]: Islamic State of Iraq and the Levant\n  *[SDGs]: Sustainable Development Goals\n  *[IMF]: International Monetary Fund\n  *[UN]: United Nations\n  *[GDP]: Gross Domestic Product\n  *[UCL]: University College London\n  *[HIV]: human immunodeficiency virus\n  *[AI]: artificial intelligence\n  *[ABI]: Association of British Insurers\n  *[CMU]: Capital Markets Union\n  *[IMO]: International Maritime Organization\n  *[MARPOL]: International Convention for the Prevention of Pollution from Ships.\n  *[UK]: United Kingdom\n  *[IGF]: International Code of Safety for Ships using Gases or other Low-flashpoint Fuels\n  *[COP]: United Nations Climate Change Conference (Conference of Parties)\n  *[AOA]: The Airport Operators Association\n  *[BATA]: British Air Transport Association\n  *[OECD]: The Organisation for Economic Co-operation and Development\n  *[PISA]: Programme for International Student Assessment\n  *[PIRLS]: Progress in International Reading Literacy Study\n  *[TIMSS]: Trends in International Mathematics and Science Study\n  *[DCMS]: Department for Digital Culture Media & Sport\n  *[CEOs]: chief executive officers\n  *[HR]: human resources\n  *[NASBM]: National Association of School Business Management\n  *[CAMHS]: Child and Adolescent Mental Health Services\n  *[EPPSE]: Effective pre-school, primary and secondary education\n  *[LAs]: local authorities\n  *[PVIs]: private, voluntary and independents\n  *[UNDP]: United Nations Development Programme\n  *[BIT]: Behavioural Insights Team\n  *[QOF]: Quality Outcomes Framework\n  *[\n  NICs\n ]: National Insurance Contributions\n  *[UKTI]: UK Trade and Investment\n  *[IPOs]: initial public offerings\n  *[DfE]: Department for Education\n  *[FSM]: free school meals\n  *[RAISEonline]: Reporting and Analysis for Improvement through School Self Evaluation Online\n  *[GSHA]: Grammar School Heads Association\n  *[OSA]: Office of the Schools Adjudicator\n  *[LACA]: Leading Association for Catering in Education\n  *[ODA]: Official Development Assistance\n  *[NGOs]: non-governmental organisations\n  *[NGO]: non-governmental organisation\n  *[BII]: British Investment International\n  *[DFID]: Department for International Development\n  *[UKEF]: UK Export Finance\n  *[COPs]: *[COP]: United Nations Climate Change Conferences\n  *[UNGA]: United Nations General Assembly\n  *[IDA]: International Development Association\n  *[IBRD]: International Bank for Reconstruction and Development\n  *[IFC]: International Finance Corporation\n  *[IDA20]: World Bank launched an early twentieth replenishment process of the International Development Association\n  *[SDG]: Sustainable Development Goal\n  *[GRF]: Global Refugee Forum\n  *[SAF]: Sudanese Armed Forces\n  *[RSF]: Rapid Support Forces",
        "I afraid you will have to make do with me, Mr Speaker.\n  *[ISIL]: Islamic State of Iraq and the Levant\n  *[SDGs]: Sustainable Development Goals\n  *[IMF]: International Monetary Fund\n  *[UN]: United Nations\n  *[GDP]: Gross Domestic Product\n  *[UCL]: University College London\n  *[HIV]: human immunodeficiency virus\n  *[AI]: artificial intelligence\n  *[ABI]: Association of British Insurers\n  *[CMU]: Capital Markets Union\n  *[IMO]: International Maritime Organization\n  *[MARPOL]: International Convention for the Prevention of Pollution from Ships.\n  *[UK]: United Kingdom\n  *[IGF]: International Code of Safety for Ships using Gases or other Low-flashpoint Fuels\n  *[COP]: United Nations Climate Change Conference (Conference of Parties)\n  *[AOA]: The Airport Operators Association\n  *[BATA]: British Air Transport Association\n  *[OECD]: The Organisation for Economic Co-operation and Development\n  *[PISA]: Programme for International Student Assessment\n  *[PIRLS]: Progress in International Reading Literacy Study\n  *[TIMSS]: Trends in International Mathematics and Science Study\n  *[DCMS]: Department for Digital Culture Media & Sport\n  *[CEOs]: chief executive officers\n  *[HR]: human resources\n  *[NASBM]: National Association of School Business Management\n  *[CAMHS]: Child and Adolescent Mental Health Services\n  *[EPPSE]: Effective pre-school, primary and secondary education\n  *[LAs]: local authorities\n  *[PVIs]: private, voluntary and independents\n  *[UNDP]: United Nations Development Programme\n  *[BIT]: Behavioural Insights Team\n  *[QOF]: Quality Outcomes Framework\n  *[\n  NICs\n ]: National Insurance Contributions\n  *[UKTI]: UK Trade and Investment\n  *[IPOs]: initial public offerings\n  *[DfE]: Department for Education\n  *[FSM]: free school meals\n  *[RAISEonline]: Reporting and Analysis for Improvement through School Self Evaluation Online\n  *[GSHA]: Grammar School Heads Association\n  *[OSA]: Office of the Schools Adjudicator\n  *[LACA]: Leading Association for Catering in Education\n  *[ODA]: Official Development Assistance\n  *[NGOs]: non-governmental organisations\n  *[NGO]: non-governmental organisation\n  *[BII]: British Investment International\n  *[DFID]: Department for International Development\n  *[UKEF]: UK Export Finance\n  *[COPs]: *[COP]: United Nations Climate Change Conferences\n  *[UNGA]: United Nations General Assembly\n  *[IDA]: International Development Association\n  *[IBRD]: International Bank for Reconstruction and Development\n  *[IFC]: International Finance Corporation\n  *[IDA20]: World Bank launched an early twentieth replenishment process of the International Development Association\n  *[SDG]: Sustainable Development Goal\n  *[GRF]: Global Refugee Forum\n  *[SAF]: Sudanese Armed Forces\n  *[RSF]: Rapid Support Forces",
        "The Prime Minister has taken the decision to appoint my right hon. Friend the Member for South West Surrey (Jeremy Hunt), one of the longest serving and most experienced parliamentarians, as her Chancellor. Their overriding priority is to restore financial stability in the face of volatile global conditions. We will take whatever tough decisions are necessary, and have made changes to the growth plan, which the Chancellor is waiting to update the House on as soon as this urgent question finishes.\n  *[ISIL]: Islamic State of Iraq and the Levant\n  *[SDGs]: Sustainable Development Goals\n  *[IMF]: International Monetary Fund\n  *[UN]: United Nations\n  *[GDP]: Gross Domestic Product\n  *[UCL]: University College London\n  *[HIV]: human immunodeficiency virus\n  *[AI]: artificial intelligence\n  *[ABI]: Association of British Insurers\n  *[CMU]: Capital Markets Union\n  *[IMO]: International Maritime Organization\n  *[MARPOL]: International Convention for the Prevention of Pollution from Ships.\n  *[UK]: United Kingdom\n  *[IGF]: International Code of Safety for Ships using Gases or other Low-flashpoint Fuels\n  *[COP]: United Nations Climate Change Conference (Conference of Parties)\n  *[AOA]: The Airport Operators Association\n  *[BATA]: British Air Transport Association\n  *[OECD]: The Organisation for Economic Co-operation and Development\n  *[PISA]: Programme for International Student Assessment\n  *[PIRLS]: Progress in International Reading Literacy Study\n  *[TIMSS]: Trends in International Mathematics and Science Study\n  *[DCMS]: Department for Digital Culture Media & Sport\n  *[CEOs]: chief executive officers\n  *[HR]: human resources\n  *[NASBM]: National Association of School Business Management\n  *[CAMHS]: Child and Adolescent Mental Health Services\n  *[EPPSE]: Effective pre-school, primary and secondary education\n  *[LAs]: local authorities\n  *[PVIs]: private, voluntary and independents\n  *[UNDP]: United Nations Development Programme\n  *[BIT]: Behavioural Insights Team\n  *[QOF]: Quality Outcomes Framework\n  *[\n  NICs\n ]: National Insurance Contributions\n  *[UKTI]: UK Trade and Investment\n  *[IPOs]: initial public offerings\n  *[DfE]: Department for Education\n  *[FSM]: free school meals\n  *[RAISEonline]: Reporting and Analysis for Improvement through School Self Evaluation Online\n  *[GSHA]: Grammar School Heads Association\n  *[OSA]: Office of the Schools Adjudicator\n  *[LACA]: Leading Association for Catering in Education\n  *[ODA]: Official Development Assistance\n  *[NGOs]: non-governmental organisations\n  *[NGO]: non-governmental organisation\n  *[BII]: British Investment International\n  *[DFID]: Department for International Development\n  *[UKEF]: UK Export Finance\n  *[COPs]: *[COP]: United Nations Climate Change Conferences\n  *[UNGA]: United Nations General Assembly\n  *[IDA]: International Development Association\n  *[IBRD]: International Bank for Reconstruction and Development\n  *[IFC]: International Finance Corporation\n  *[IDA20]: World Bank launched an early twentieth replenishment process of the International Development Association\n  *[SDG]: Sustainable Development Goal\n  *[GRF]: Global Refugee Forum\n  *[SAF]: Sudanese Armed Forces\n  *[RSF]: Rapid Support Forces"
    ]
}